crypto_strategy/__init__.py
crypto_strategy/data.py
crypto_strategy/commands/__init__.py
crypto_strategy/commands/cli.py
crypto_strategy/portfolio/__init__.py
crypto_strategy/portfolio/portfolio_utils.py
crypto_strategy/portfolio/portfolio_weighting.py
crypto_strategy/reporting/__init__.py
crypto_strategy/reporting/base.py
crypto_strategy/reporting/plot.py
crypto_strategy/reporting/report.py
crypto_strategy/strategies/__init__.py
crypto_strategy/strategies/base.py
crypto_strategy/strategies/bo_strategy.py
crypto_strategy/strategies/ma_strategy.py
crypto_strategy/strategies/macd_strategy.py
finlab_crypto/__init__.py
finlab_crypto/chart.py
finlab_crypto/crawler.py
finlab_crypto/indicators.py
finlab_crypto/online.py
finlab_crypto/overfitting.py
finlab_crypto/strategy.py
finlab_crypto/utility.py
crypto_strategy-0.1.20.dist-info/LICENSE
crypto_strategy-0.1.20.dist-info/METADATA
crypto_strategy-0.1.20.dist-info/WHEEL
crypto_strategy-0.1.20.dist-info/entry_points.txt
crypto_strategy-0.1.20.dist-info/top_level.txt
crypto_strategy-0.1.20.dist-info/RECORD
