Metadata-Version: 2.1
Name: crypto-strategy
Version: 0.1.20
Summary: Repo to create crypto strategies
Home-page: https://github.com/minggnim/crypto-strategy
Author: Ming Gao
Author-email: ming_gao@outlook.com
Classifier: Programming Language :: Python :: 3
Classifier: License :: OSI Approved :: GNU General Public License v3 (GPLv3)
Classifier: Operating System :: OS Independent
Requires-Python: >=3.6
License-File: LICENSE
Requires-Dist: numba
Requires-Dist: numpy
Requires-Dist: pandas
Requires-Dist: vectorbt
Requires-Dist: ta-lib-bin
Requires-Dist: python-binance
Provides-Extra: full
Requires-Dist: tqdm ; extra == 'full'
Requires-Dist: click ; extra == 'full'
Requires-Dist: statsmodels ; extra == 'full'
Requires-Dist: pyecharts ; extra == 'full'
Requires-Dist: seaborn ; extra == 'full'
